async_bybit_p2p/__init__.py
async_bybit_p2p/_exceptions.py
async_bybit_p2p/_p2p_helper.py
async_bybit_p2p/_p2p_manager.py
async_bybit_p2p/_p2p_method.py
async_bybit_p2p/p2p.py
async_bybit_p2p/p2p_requests.py
async_bybit_p2p-1.0.4.dist-info/licenses/LICENSE
async_bybit_p2p-1.0.4.dist-info/METADATA
async_bybit_p2p-1.0.4.dist-info/WHEEL
async_bybit_p2p-1.0.4.dist-info/top_level.txt
async_bybit_p2p-1.0.4.dist-info/RECORD
