Metadata-Version: 2.4
Name: async_bybit_p2p
Version: 1.0.4
Summary: An asynchronous fork of the official ByBit P2P API integration library written in Python.
Author-email: Kirill Suvorov <herbalsomml@gmail.com>
License-Expression: MIT
Project-URL: Homepage, https://github.com/TokenatorObmenator/async_bybit_p2p
Project-URL: Issues, https://github.com/TokenatorObmenator/async_bybit_p2p/issues
Classifier: Programming Language :: Python :: 3
Classifier: Operating System :: OS Independent
Requires-Python: >=3.11
License-File: LICENSE
Requires-Dist: aiofiles
Requires-Dist: aiohttp
Requires-Dist: pycryptodome
Dynamic: license-file
